AUTHORS
COPYING
README.md
setup.py
PyPlucker/AliasList.py
PyPlucker/ConfigFiles.py
PyPlucker/ConversionParser.py
PyPlucker/Decode.py
PyPlucker/ExclusionList.py
PyPlucker/ImageParser.py
PyPlucker/PalmImagePlugin.py
PyPlucker/Parser.py
PyPlucker/PluckerDocs.py
PyPlucker/PluckerLinks.py
PyPlucker/Profiling.py
PyPlucker/Retriever.py
PyPlucker/Spider.py
PyPlucker/TextParser.py
PyPlucker/Url.py
PyPlucker/UtilFns.py
PyPlucker/Writer.py
PyPlucker/__init__.py
PyPlucker/rfc822py3.py
PyPlucker/sgmllib.py
PyPlucker.egg-info/PKG-INFO
PyPlucker.egg-info/SOURCES.txt
PyPlucker.egg-info/dependency_links.txt
PyPlucker.egg-info/requires.txt
PyPlucker.egg-info/top_level.txt
PyPlucker/helper/CharsetMapping.py
PyPlucker/helper/PQAAppInfo.py
PyPlucker/helper/__init__.py
PyPlucker/helper/dict.py
PyPlucker/helper/doc_compress.py
PyPlucker/helper/gettext.py
PyPlucker/helper/prc.py
PyPlucker/helper/timeoutsocket.py
bin/plucker-build