Metadata-Version: 2.1
Name: PyPlucker
Version: 3.7
Summary: Web and document parser, converter and scraper for Plucker, the Palm OS app
Home-page: https://github.com/lxmx/PyPlucker
Author: Vasily Mikhaylichenko
Author-email: vasily@lxmx.org
License: GPLv2
Classifier: Development Status :: 5 - Production/Stable
Classifier: License :: OSI Approved :: GNU General Public License v2 (GPLv2)
Classifier: Environment :: Console
Classifier: Intended Audience :: Developers
Classifier: Intended Audience :: End Users/Desktop
Classifier: Operating System :: OS Independent
Classifier: Operating System :: PDA Systems
Classifier: Programming Language :: Python
Classifier: Programming Language :: Python :: 3
Classifier: Topic :: Utilities
Classifier: Topic :: Education
Classifier: Topic :: Text Processing
Classifier: Topic :: Multimedia :: Graphics :: Graphics Conversion
License-File: COPYING
License-File: AUTHORS
